covid19_supermarket_abm/__init__.py
covid19_supermarket_abm/core.py
covid19_supermarket_abm/path_generators.py
covid19_supermarket_abm/simulator.py
covid19_supermarket_abm/example_data/__init__.py
covid19_supermarket_abm/example_data/edgelist.tsv
covid19_supermarket_abm/example_data/edgelist_oneway.tsv
covid19_supermarket_abm/example_data/shelf_to_zone.csv
covid19_supermarket_abm/example_data/shelves.json
covid19_supermarket_abm/example_data/zone_paths.json
covid19_supermarket_abm/example_data/zones.csv
covid19_supermarket_abm/utils/__init__.py
covid19_supermarket_abm/utils/create_store_network.py
covid19_supermarket_abm/utils/create_synthetic_baskets.py
covid19_supermarket_abm/utils/create_synthetic_store_network.py
covid19_supermarket_abm/utils/istarmap.py
covid19_supermarket_abm/utils/load_example_data.py
covid19_supermarket_abm/utils/shelf_class.py
covid19_supermarket_abm-0.0.5.dist-info/LICENSE
covid19_supermarket_abm-0.0.5.dist-info/METADATA
covid19_supermarket_abm-0.0.5.dist-info/WHEEL
covid19_supermarket_abm-0.0.5.dist-info/top_level.txt
covid19_supermarket_abm-0.0.5.dist-info/RECORD
