Metadata-Version: 2.1
Name: covid19-supermarket-abm
Version: 0.0.5
Summary: Agent-based model for Covid-19 transmission in supermarkets
Home-page: https://github.com/fabianying/covid19-supermarket-abm
Author: Fabian Ying
Author-email: fabian.m.ying@gmail.com
License: UNKNOWN
Platform: UNKNOWN
Classifier: Programming Language :: Python :: 3
Classifier: License :: OSI Approved :: GNU General Public License (GPL)
Classifier: Operating System :: OS Independent
Requires-Python: >=3.6
Requires-Dist: pandas (>=0.24.2)
Requires-Dist: numpy (>=1.16.2)
Requires-Dist: simpy (>=4.0.1)
Requires-Dist: matplotlib (>=3.1.0)
Requires-Dist: networkx (>=2.5)
Requires-Dist: tqdm
Requires-Dist: pyarrow (>=0.16.0)
